{
  "name": "Amazon ESCI-S",
  "entity_name": null,
  "entity_name_plural": null,
  "short_description": "1.6M Products",
  "created_at": "2023-11-02T13:36:40.055Z",
  "changed_at": "2024-05-30T13:54:11.011Z",
  "primary_key": "asin",
  "thumbnail_image": "image",
  "descriptive_text_fields": [
    "title",
    "bullets",
    "description"
  ],
  "default_search_fields": [
    "title",
    "bullets",
    "description",
    "title_description_e5_base"
  ],
  "advanced_options": {},
  "result_list_rendering": {
    "url": "(item) => { return null }",
    "body": "(item) => { return item.description }",
    "image": "(item) => { return item.image }",
    "title": "(item) => { return item.title }",
    "subtitle": "(item) => { return item.price ? item.price.toFixed(2) : '' }",
    "required_fields": [
      "title",
      "description",
      "image",
      "price"
    ]
  },
  "hover_label_rendering": {
    "image": "(item) => { return item.image }",
    "title": "(item) => { return item.title }",
    "subtitle": "(item) => { return null }",
    "required_fields": [
      "title",
      "image"
    ]
  },
  "detail_view_rendering": {
    "url": "(item) => { return null }",
    "body": "(item) => { return null }",
    "image": "(item) => { return null }",
    "title": "(item) => { return null }",
    "subtitle": "(item) => { return null }",
    "required_fields": []
  },
  "statistics": {},
  "applicable_import_converters": [],
  "applicable_export_converters": [],
  "identifier": "amazon_esci-s",
  "object_fields": [
    {
      "identifier": "type",
      "name": null,
      "created_at": "2023-11-02T13:39:53.731Z",
      "changed_at": "2024-05-30T13:54:10.996Z",
      "schema": "amazon_esci-s",
      "description": null,
      "field_type": "TAG",
      "is_array": false,
      "language_analysis": "",
      "embedding_space": null,
      "is_available_for_search": false,
      "text_similarity_threshold": null,
      "image_similarity_threshold": null,
      "is_available_for_filtering": true,
      "index_parameters": {},
      "generator": null,
      "generator_parameters": null,
      "generating_condition": "",
      "source_fields": [],
      "should_be_generated": false,
      "_order": 0
    },
    {
      "identifier": "locale",
      "name": null,
      "created_at": "2023-11-02T13:39:53.732Z",
      "changed_at": "2024-05-30T13:54:10.997Z",
      "schema": "amazon_esci-s",
      "description": null,
      "field_type": "TAG",
      "is_array": false,
      "language_analysis": "",
      "embedding_space": null,
      "is_available_for_search": false,
      "text_similarity_threshold": null,
      "image_similarity_threshold": null,
      "is_available_for_filtering": true,
      "index_parameters": {},
      "generator": null,
      "generator_parameters": null,
      "generating_condition": "",
      "source_fields": [],
      "should_be_generated": false,
      "_order": 1
    },
    {
      "identifier": "asin",
      "name": null,
      "created_at": "2023-11-02T13:39:53.732Z",
      "changed_at": "2024-05-30T13:54:10.998Z",
      "schema": "amazon_esci-s",
      "description": null,
      "field_type": "IDENTIFIER",
      "is_array": false,
      "language_analysis": "",
      "embedding_space": null,
      "is_available_for_search": false,
      "text_similarity_threshold": null,
      "image_similarity_threshold": null,
      "is_available_for_filtering": true,
      "index_parameters": {},
      "generator": null,
      "generator_parameters": null,
      "generating_condition": "",
      "source_fields": [],
      "should_be_generated": false,
      "_order": 2
    },
    {
      "identifier": "title",
      "name": null,
      "created_at": "2023-11-02T13:39:53.732Z",
      "changed_at": "2024-05-30T13:54:10.999Z",
      "schema": "amazon_esci-s",
      "description": null,
      "field_type": "TEXT",
      "is_array": false,
      "language_analysis": "english",
      "embedding_space": null,
      "is_available_for_search": true,
      "text_similarity_threshold": null,
      "image_similarity_threshold": null,
      "is_available_for_filtering": false,
      "index_parameters": {},
      "generator": null,
      "generator_parameters": null,
      "generating_condition": "",
      "source_fields": [],
      "should_be_generated": false,
      "_order": 3
    },
    {
      "identifier": "stars",
      "name": null,
      "created_at": "2023-11-02T13:39:53.732Z",
      "changed_at": "2024-05-30T13:54:11.000Z",
      "schema": "amazon_esci-s",
      "description": null,
      "field_type": "FLOAT",
      "is_array": false,
      "language_analysis": "",
      "embedding_space": null,
      "is_available_for_search": false,
      "text_similarity_threshold": null,
      "image_similarity_threshold": null,
      "is_available_for_filtering": true,
      "index_parameters": {},
      "generator": null,
      "generator_parameters": null,
      "generating_condition": "",
      "source_fields": [],
      "should_be_generated": false,
      "_order": 4
    },
    {
      "identifier": "ratings",
      "name": null,
      "created_at": "2023-11-02T13:39:53.732Z",
      "changed_at": "2024-05-30T13:54:11.001Z",
      "schema": "amazon_esci-s",
      "description": null,
      "field_type": "INTEGER",
      "is_array": false,
      "language_analysis": "",
      "embedding_space": null,
      "is_available_for_search": false,
      "text_similarity_threshold": null,
      "image_similarity_threshold": null,
      "is_available_for_filtering": true,
      "index_parameters": {},
      "generator": null,
      "generator_parameters": null,
      "generating_condition": "",
      "source_fields": [],
      "should_be_generated": false,
      "_order": 5
    },
    {
      "identifier": "category",
      "name": null,
      "created_at": "2023-11-02T13:39:53.733Z",
      "changed_at": "2024-05-30T13:54:11.002Z",
      "schema": "amazon_esci-s",
      "description": null,
      "field_type": "TAG",
      "is_array": true,
      "language_analysis": "",
      "embedding_space": null,
      "is_available_for_search": true,
      "text_similarity_threshold": null,
      "image_similarity_threshold": null,
      "is_available_for_filtering": true,
      "index_parameters": {},
      "generator": null,
      "generator_parameters": null,
      "generating_condition": "",
      "source_fields": [],
      "should_be_generated": false,
      "_order": 6
    },
    {
      "identifier": "attrs",
      "name": null,
      "created_at": "2023-11-02T13:39:53.733Z",
      "changed_at": "2024-05-30T13:54:11.003Z",
      "schema": "amazon_esci-s",
      "description": null,
      "field_type": "ARBITRARY_OBJECT",
      "is_array": false,
      "language_analysis": "",
      "embedding_space": null,
      "is_available_for_search": false,
      "text_similarity_threshold": null,
      "image_similarity_threshold": null,
      "is_available_for_filtering": true,
      "index_parameters": {},
      "generator": null,
      "generator_parameters": null,
      "generating_condition": "",
      "source_fields": [],
      "should_be_generated": false,
      "_order": 7
    },
    {
      "identifier": "bullets",
      "name": null,
      "created_at": "2023-11-02T13:42:05.520Z",
      "changed_at": "2024-05-30T13:54:11.004Z",
      "schema": "amazon_esci-s",
      "description": null,
      "field_type": "TEXT",
      "is_array": true,
      "language_analysis": "english",
      "embedding_space": null,
      "is_available_for_search": true,
      "text_similarity_threshold": null,
      "image_similarity_threshold": null,
      "is_available_for_filtering": false,
      "index_parameters": {},
      "generator": null,
      "generator_parameters": null,
      "generating_condition": "",
      "source_fields": [],
      "should_be_generated": false,
      "_order": 8
    },
    {
      "identifier": "description",
      "name": null,
      "created_at": "2023-11-02T13:42:05.520Z",
      "changed_at": "2024-05-30T13:54:11.005Z",
      "schema": "amazon_esci-s",
      "description": null,
      "field_type": "TEXT",
      "is_array": false,
      "language_analysis": "english",
      "embedding_space": null,
      "is_available_for_search": true,
      "text_similarity_threshold": null,
      "image_similarity_threshold": null,
      "is_available_for_filtering": false,
      "index_parameters": {},
      "generator": null,
      "generator_parameters": null,
      "generating_condition": "",
      "source_fields": [],
      "should_be_generated": false,
      "_order": 9
    },
    {
      "identifier": "reviews",
      "name": null,
      "created_at": "2023-11-02T13:42:05.520Z",
      "changed_at": "2024-05-30T13:54:11.006Z",
      "schema": "amazon_esci-s",
      "description": null,
      "field_type": "ATTRIBUTES",
      "is_array": false,
      "language_analysis": "english",
      "embedding_space": null,
      "is_available_for_search": false,
      "text_similarity_threshold": null,
      "image_similarity_threshold": null,
      "is_available_for_filtering": false,
      "index_parameters": {},
      "generator": null,
      "generator_parameters": null,
      "generating_condition": "",
      "source_fields": [],
      "should_be_generated": false,
      "_order": 10
    },
    {
      "identifier": "price",
      "name": null,
      "created_at": "2023-11-02T13:42:05.520Z",
      "changed_at": "2024-05-30T13:54:11.007Z",
      "schema": "amazon_esci-s",
      "description": null,
      "field_type": "FLOAT",
      "is_array": false,
      "language_analysis": "",
      "embedding_space": null,
      "is_available_for_search": false,
      "text_similarity_threshold": null,
      "image_similarity_threshold": null,
      "is_available_for_filtering": true,
      "index_parameters": {},
      "generator": null,
      "generator_parameters": null,
      "generating_condition": "",
      "source_fields": [],
      "should_be_generated": false,
      "_order": 11
    },
    {
      "identifier": "image",
      "name": null,
      "created_at": "2023-11-02T13:42:05.520Z",
      "changed_at": "2024-05-30T13:54:11.008Z",
      "schema": "amazon_esci-s",
      "description": null,
      "field_type": "IMAGE",
      "is_array": false,
      "language_analysis": "",
      "embedding_space": null,
      "is_available_for_search": false,
      "text_similarity_threshold": null,
      "image_similarity_threshold": null,
      "is_available_for_filtering": false,
      "index_parameters": {},
      "generator": null,
      "generator_parameters": null,
      "generating_condition": "",
      "source_fields": [],
      "should_be_generated": false,
      "_order": 12
    },
    {
      "identifier": "reviews.text",
      "name": null,
      "created_at": "2023-11-07T11:07:41.576Z",
      "changed_at": "2024-05-30T13:54:11.009Z",
      "schema": "amazon_esci-s",
      "description": null,
      "field_type": "TEXT",
      "is_array": false,
      "language_analysis": "english",
      "embedding_space": null,
      "is_available_for_search": true,
      "text_similarity_threshold": null,
      "image_similarity_threshold": null,
      "is_available_for_filtering": false,
      "index_parameters": {},
      "generator": null,
      "generator_parameters": null,
      "generating_condition": "",
      "source_fields": [],
      "should_be_generated": false,
      "_order": 13
    },
    {
      "identifier": "title_description_e5_base",
      "name": null,
      "created_at": "2023-11-10T17:41:47.554Z",
      "changed_at": "2024-05-30T13:54:11.010Z",
      "schema": "amazon_esci-s",
      "description": null,
      "field_type": "VECTOR",
      "is_array": false,
      "language_analysis": null,
      "embedding_space": null,
      "is_available_for_search": true,
      "text_similarity_threshold": null,
      "image_similarity_threshold": null,
      "is_available_for_filtering": false,
      "index_parameters": {},
      "generator": "e5_base_text_embedding",
      "generator_parameters": null,
      "generating_condition": "",
      "source_fields": [
        "title",
        "description"
      ],
      "should_be_generated": false,
      "_order": 14
    }
  ]
}